<?xml version="1.0" encoding="UTF-8"?>
<?xml-model href="https://pds.nasa.gov/pds4/pds/v1/PDS4_PDS_1M00.sch" schematypens="http://purl.oclc.org/dsdl/schematron"?>

<Product_Document xmlns="http://pds.nasa.gov/pds4/pds/v1"
    xmlns:xsi="http://www.w3.org/2001/XMLSchema-instance"
    xsi:schemaLocation="http://pds.nasa.gov/pds4/pds/v1 http://pds.nasa.gov/pds4/pds/v1/PDS4_PDS_1M00.xsd">
    
    <Identification_Area>
        <logical_identifier>urn:nasa:pds:context_support:document:ice_description</logical_identifier>
        <version_id>1.0</version_id>
        <title>International Sun-Earth Explorer-3/International Cometary Explorer Description</title>
        <information_model_version>1.22.0.0</information_model_version>
        <product_class>Product_Document</product_class>
        
        <Citation_Information>
            <publication_year>2024</publication_year>
            <description>
                The bulk of this document is reformatted from the DESCRIPTION of the 
                PDS3 mission catalog file (c.1992), which was unattributed. A note was 
                added to the original text, summarizing the end of mission and 2014 
                attempt to reclaim the spacecraft.
            </description>
            <List_Author>
                <Organization>
                    <organization_name>Unknown Author</organization_name>
                </Organization>
                <Person>
                    <given_name>Anne</given_name>
                    <family_name>Raugh</family_name>
                    <person_orcid>https://orcid.org/0000-0002-8300-9443</person_orcid>
                </Person>
            </List_Author>
        </Citation_Information>
    </Identification_Area>
    <Document>
        <publication_date>2024</publication_date>
        <Document_Edition>
            <edition_name>MSWord</edition_name>
            <language>English</language>
            <files>1</files>
            <Document_File>
                <file_name>ice.docx</file_name>
                <document_standard_id>Microsoft Word</document_standard_id>
            </Document_File>
        </Document_Edition>
    </Document>
</Product_Document>