<?xml version='1.0' encoding='utf-8'?>
<?xml-model href="https://pds.nasa.gov/pds4/pds/v1/PDS4_PDS_1M00.sch" schematypens="http://purl.oclc.org/dsdl/schematron"?>
<?xml-model href="https://pds.nasa.gov/pds4/ctli/v2/PDS4_CTLI_1M00_2100.sch" schematypens="http://purl.oclc.org/dsdl/schematron"?>
<Product_Context xmlns="http://pds.nasa.gov/pds4/pds/v1" xmlns:xsi="http://www.w3.org/2001/XMLSchema-instance" xmlns:ctli="http://pds.nasa.gov/pds4/ctli/v2" xsi:schemaLocation="http://pds.nasa.gov/pds4/pds/v1 https://pds.nasa.gov/pds4/pds/v1/PDS4_PDS_1M00.xsd http://pds.nasa.gov/pds4/ctli/v2 https://pds.nasa.gov/pds4/ctli/v2/PDS4_CTLI_1M00_2100.xsd">
  <Identification_Area>
    <logical_identifier>urn:nasa:pds:context:instrument:meca_tecp.phx</logical_identifier>
    <version_id>1.1</version_id>
    <title>Phoenix Lander Microscopy, Electrochemistry, and Conductivity Analyzer Thermal and Electrical Conductivity Probe</title>
    <information_model_version>1.22.0.0</information_model_version>
    <product_class>Product_Context</product_class>
    <Alias_List>
      <Alias>
        <alternate_title>MECA THERMAL AND ELECTRICAL CONDUCTIVITY PROBE for PHX</alternate_title>
      </Alias>
      <Alias>
        <alternate_title>MECA THERMAL AND ELECTRICAL CONDUCTIVITY PROBE</alternate_title>
      </Alias>
    </Alias_List>
    <Modification_History>
      <Modification_Detail>
        <modification_date>2025-01-02</modification_date>
        <version_id>1.1</version_id>
        <description>Updated schema version. Adding missing "investigation" references.</description>
      </Modification_Detail>
      <Modification_Detail>
        <modification_date>2018-05-23</modification_date>
        <version_id>1.0</version_id>
        <description>Changed logical_identifier from meca_tecp__phx to meca_tecp.phx</description>
      </Modification_Detail>
    </Modification_History>
  </Identification_Area>
  <Reference_List>
    <Internal_Reference>
      <lid_reference>urn:nasa:pds:context:investigation:mission.phoenix</lid_reference>
      <reference_type>instrument_to_investigation</reference_type>
    </Internal_Reference>
    <Internal_Reference>
      <lid_reference>urn:nasa:pds:context:instrument_host:spacecraft.phx</lid_reference>
      <reference_type>instrument_to_instrument_host</reference_type>
    </Internal_Reference>
    <External_Reference>
      <reference_text>
                   Zent, A., M.H. Hecht, D. Cobos, G. Cardell, M.C. Foote, S.E. Woods, M. Mehta.
                   The Thermal Electrical Conductivity Probe (TECP) for Phoenix, J. Geophys. Res.,
                   in press, 2008.
            </reference_text>
      <description>reference.ZENTETAL2008</description>
    </External_Reference>
  </Reference_List>
  <Instrument>
    <name>Phoenix Lander Microscopy, Electrochemistry, and Conductivity Analyzer Thermal and Electrical Conductivity Probe</name>
    <type>Regolith Properties</type>
    <!--RChen/EN was Probe-->
    <naif_instrument_id>not applicable</naif_instrument_id>
    <serial_number>not applicable</serial_number>
    <description>The Phoenix Lander Microscopy, Electrochemistry, and Conductivity Analyzer (MECA) instrument suite was composed of an Atomic Force Microscope (AFM), a Thermal Electrical Conductivity Probe (TECP) and a Wet Chemistry Laboratory (WCL). The TECP was designed to study the thermal properties of the Martian soil. The probe measured how heat and electrical currents traveled through the soil, providing key information about the thermal conductivity and electrical properties of the surface material. These data helped scientists understand the soil's ability to retain heat, its moisture content, and how it might interact with the Martian environment. The information gathered by this probe contributed to assessing the presence of water ice and the potential for future human exploration of Mars, as well as providing a better understanding of the planet's surface composition and behavior.</description>
  </Instrument>
</Product_Context>
